gat/__init__.py
gat/coCollection.py
gat/coPath.py
gat/coS3.py
gat/coSsh.py
gat/gat.py
gat/gatHelper.py
gat/myutil.py
gat/plugin.py
gat/sa.py
gat/sampleFiles.py
test/__init__.py
test/test_gatHelper.py
god_tool-0.9.0.dist-info/LICENSE.txt
god_tool-0.9.0.dist-info/METADATA
god_tool-0.9.0.dist-info/WHEEL
god_tool-0.9.0.dist-info/entry_points.txt
god_tool-0.9.0.dist-info/top_level.txt
god_tool-0.9.0.dist-info/RECORD
