Metadata-Version: 2.1
Name: god-tool
Version: 0.9.0
Summary: Provisioning and App deployment tool.
Home-page: https://github.com/cjng96/gat
Author: Felix Choi
Author-email: cjng96@gmail.com
License: LGPL
Keywords: auto restart,deployment
Platform: Posix; MacOS X; Windows
Classifier: Operating System :: OS Independent
Classifier: Programming Language :: Python
Classifier: Programming Language :: Python :: 3
Classifier: Programming Language :: Python :: 3.2
Classifier: Programming Language :: Python :: 3.3
Classifier: Programming Language :: Python :: 3.4
Classifier: Programming Language :: Python :: 3.5
Classifier: Programming Language :: Python :: 3.6
Classifier: Programming Language :: Python :: 3.7
Classifier: Programming Language :: Python :: 3.8
Requires-Python: >=3
License-File: LICENSE.txt
Requires-Dist: paramiko
Requires-Dist: watchdog
Requires-Dist: PyYAML
